Flask_Apify-0.7.1.dist-info/DESCRIPTION.rst
Flask_Apify-0.7.1.dist-info/METADATA
Flask_Apify-0.7.1.dist-info/RECORD
Flask_Apify-0.7.1.dist-info/WHEEL
Flask_Apify-0.7.1.dist-info/metadata.json
Flask_Apify-0.7.1.dist-info/top_level.txt
flask_apify/__init__.py
flask_apify/exc.py
flask_apify/fy.py
flask_apify/http.py
flask_apify/utils.py
flask_apify/serializers/__init__.py
flask_apify/serializers/debug.py
flask_apify/serializers/json.py
flask_apify/serializers/jsonp.py
